processing_py/__init__.py
processing_py/app.py
processing_py/color.py
processing_py/constants.py
processing_py/i3_jython.py
processing_py/listener.py
processing_py/requirements.py
processing_py-0.3.7.dist-info/LICENSE
processing_py-0.3.7.dist-info/METADATA
processing_py-0.3.7.dist-info/WHEEL
processing_py-0.3.7.dist-info/top_level.txt
processing_py-0.3.7.dist-info/RECORD
