Metadata-Version: 2.1
Name: processing_py
Version: 0.3.7
Summary: Graphics Library for Python
Home-page: https://github.com/FarukHammoud/processing_py
Author: Faruk Hammoud
Author-email: farukhammoud@student-cs.fr
License: UNKNOWN
Platform: UNKNOWN
Classifier: Programming Language :: Python :: 3
Classifier: License :: OSI Approved :: MIT License
Classifier: Operating System :: OS Independent
Requires-Python: >=3.6
